edge_core/__init__.py
edge_core/decode_protobuf.py
edge_core/encode_protobuf.py
edge_core/datatypes/__init__.py
edge_core/datatypes/data_source_property_pb2.py
edge_core/datatypes/data_source_property_pb2_grpc.py
edge_core/datatypes/io_common_pb2.py
edge_core/datatypes/io_common_pb2_grpc.py
edge_core/datatypes/io_control_pb2.py
edge_core/datatypes/io_control_pb2_grpc.py
edge_core/datatypes/io_property_pb2.py
edge_core/datatypes/io_property_pb2_grpc.py
edge_core/datatypes/remote_io_payload_pb2.py
edge_core/datatypes/remote_io_payload_pb2_grpc.py
edge_core/datatypes/service_io_control_pb2.py
edge_core/datatypes/service_io_control_pb2_grpc.py
edge_core/datatypes/sinker_payload_pb2.py
edge_core/datatypes/sinker_payload_pb2_grpc.py
edge_core/helpers/__init__.py
edge_core/helpers/dict_control.py
edge_core/helpers/time.py
kornic.io.datatypes-1.0.15.1.dist-info/METADATA
kornic.io.datatypes-1.0.15.1.dist-info/WHEEL
kornic.io.datatypes-1.0.15.1.dist-info/top_level.txt
kornic.io.datatypes-1.0.15.1.dist-info/RECORD
