Metadata-Version: 2.1
Name: kornic.io.datatypes
Version: 1.0.15.1
Summary: Kornic Iot Communication DataTypes & API
Home-page: http://www.kornic.co.kr/
Author: kornic
Author-email: kimdh@kornic.co.kr
License: MIT
Platform: UNKNOWN
Requires-Python: >=3.9
Requires-Dist: google
Requires-Dist: protobuf (==3.20)
Requires-Dist: grpcio
Requires-Dist: numpy
